dgus_control/__init__.py
dgus_control/constants.py
dgus_control/dgus.py
dgus_control/dgus_starter.py
dgus_control/project_picker.py
dgus_control-0.1.0.dev9.dist-info/licenses/LICENSE
dgus_control-0.1.0.dev9.dist-info/METADATA
dgus_control-0.1.0.dev9.dist-info/WHEEL
dgus_control-0.1.0.dev9.dist-info/top_level.txt
dgus_control-0.1.0.dev9.dist-info/RECORD
