Metadata-Version: 2.4
Name: dgus-control
Version: 0.1.0.dev9
Summary: DGUS UI automation toolkit (not affiliated with or endorsed by DWIN Technology or DGUS)
Author-email: TheRealRazbi <therealrazbi@users.noreply.github.com>
License: Mozilla Public License Version 2.0
Project-URL: Homepage, https://github.com/TheRealRazbi/dgus-control
Project-URL: Bug Tracker, https://github.com/TheRealRazbi/dgus-control/issues
Keywords: dgus,automation,ui automation,template matching,runner
Classifier: Programming Language :: Python :: 3
Classifier: Programming Language :: Python :: 3.11
Classifier: Operating System :: Microsoft :: Windows
Classifier: License :: OSI Approved :: Mozilla Public License 2.0 (MPL 2.0)
Requires-Python: >=3.11
License-File: LICENSE
Requires-Dist: stage-click<1.0,>=0.0.1.dev2
Dynamic: license-file
